{
  "annotations": {
    "list": [
      {
        "builtIn": 1,
        "datasource": {
          "type": "grafana",
          "uid": "-- Grafana --"
        },
        "enable": true,
        "hide": true,
        "iconColor": "rgba(0, 211, 255, 1)",
        "name": "Annotations & Alerts",
        "target": {
          "limit": 100,
          "matchAny": false,
          "tags": [],
          "type": "dashboard"
        },
        "type": "dashboard"
      }
    ]
  },
  "editable": true,
  "fiscalYearStartMonth": 0,
  "graphTooltip": 0,
  "id": 34,
  "links": [],
  "liveNow": false,
  "panels": [
    {
      "datasource": {
        "type": "prometheus",
        "uid": "${datasource}"
      },
      "fieldConfig": {
        "defaults": {
          "color": {
            "mode": "palette-classic"
          },
          "custom": {
            "axisBorderShow": false,
            "axisCenteredZero": false,
            "axisColorMode": "text",
            "axisLabel": "",
            "axisPlacement": "auto",
            "barAlignment": 0,
            "drawStyle": "line",
            "fillOpacity": 0,
            "gradientMode": "none",
            "hideFrom": {
              "legend": false,
              "tooltip": false,
              "viz": false
            },
            "insertNulls": false,
            "lineInterpolation": "linear",
            "lineWidth": 1,
            "pointSize": 5,
            "scaleDistribution": {
              "type": "linear"
            },
            "showPoints": "auto",
            "spanNulls": false,
            "stacking": {
              "group": "A",
              "mode": "none"
            },
            "thresholdsStyle": {
              "mode": "off"
            }
          },
          "mappings": [],
          "thresholds": {
            "mode": "absolute",
            "steps": [
              {
                "color": "green",
                "value": null
              },
              {
                "color": "red",
                "value": 80
              }
            ]
          },
          "unit": "percent"
        },
        "overrides": []
      },
      "gridPos": {
        "h": 9,
        "w": 24,
        "x": 0,
        "y": 0
      },
      "id": 4,
      "options": {
        "legend": {
          "calcs": [],
          "displayMode": "list",
          "placement": "bottom",
          "showLegend": true
        },
        "tooltip": {
          "mode": "single",
          "sort": "none"
        }
      },
      "targets": [
        {
          "alias": "$tag_pid",
          "datasource": {
            "type": "prometheus",
            "uid": "${datasource}"
          },
          "disableTextWrap": false,
          "editorMode": "builder",
          "exemplar": false,
          "expr": "proc_cpu_use{instance=~\"$job\"}",
          "fullMetaSearch": false,
          "groupBy": [
            {
              "params": [
                "$cusInterval"
              ],
              "type": "time"
            },
            {
              "params": [
                "pid"
              ],
              "type": "tag"
            }
          ],
          "includeNullMetadata": true,
          "instant": false,
          "legendFormat": "{{instance}}",
          "measurement": "proc_cpu_use",
          "orderByTime": "DESC",
          "policy": "default",
          "query": "SELECT \"cpu_use\" FROM \"proc_cpu_use\" WHERE (\"pid\" =~ /^$job$/) AND $timeFilter ORDER BY time DESC",
          "range": true,
          "rawQuery": false,
          "refId": "A",
          "resultFormat": "time_series",
          "select": [
            [
              {
                "params": [
                  "cpu_use"
                ],
                "type": "field"
              },
              {
                "params": [],
                "type": "mean"
              }
            ]
          ],
          "tags": [
            {
              "key": "pid",
              "operator": "=~",
              "value": "/^$job$/"
            }
          ],
          "useBackend": false
        }
      ],
      "title": "CPU Use",
      "type": "timeseries"
    },
    {
      "datasource": {
        "type": "prometheus",
        "uid": "${datasource}"
      },
      "fieldConfig": {
        "defaults": {
          "color": {
            "mode": "palette-classic"
          },
          "custom": {
            "axisBorderShow": false,
            "axisCenteredZero": false,
            "axisColorMode": "text",
            "axisLabel": "",
            "axisPlacement": "auto",
            "barAlignment": 0,
            "drawStyle": "line",
            "fillOpacity": 0,
            "gradientMode": "none",
            "hideFrom": {
              "legend": false,
              "tooltip": false,
              "viz": false
            },
            "insertNulls": false,
            "lineInterpolation": "linear",
            "lineWidth": 1,
            "pointSize": 5,
            "scaleDistribution": {
              "type": "linear"
            },
            "showPoints": "auto",
            "spanNulls": false,
            "stacking": {
              "group": "A",
              "mode": "none"
            },
            "thresholdsStyle": {
              "mode": "off"
            }
          },
          "mappings": [],
          "thresholds": {
            "mode": "absolute",
            "steps": [
              {
                "color": "green",
                "value": null
              },
              {
                "color": "red",
                "value": 80
              }
            ]
          },
          "unit": "decbytes"
        },
        "overrides": []
      },
      "gridPos": {
        "h": 8,
        "w": 24,
        "x": 0,
        "y": 9
      },
      "id": 6,
      "options": {
        "legend": {
          "calcs": [],
          "displayMode": "list",
          "placement": "bottom",
          "showLegend": true
        },
        "tooltip": {
          "mode": "single",
          "sort": "none"
        }
      },
      "targets": [
        {
          "alias": "$tag_pid",
          "datasource": {
            "type": "prometheus",
            "uid": "${datasource}"
          },
          "disableTextWrap": false,
          "editorMode": "builder",
          "expr": "proc_mem_use{instance=~\"$job\"}",
          "fullMetaSearch": false,
          "groupBy": [
            {
              "params": [
                "$cusInterval"
              ],
              "type": "time"
            },
            {
              "params": [
                "pid"
              ],
              "type": "tag"
            }
          ],
          "includeNullMetadata": true,
          "legendFormat": "{{instance}}",
          "measurement": "proc_mem_use",
          "orderByTime": "ASC",
          "policy": "default",
          "range": true,
          "refId": "A",
          "resultFormat": "time_series",
          "select": [
            [
              {
                "params": [
                  "mem_use"
                ],
                "type": "field"
              },
              {
                "params": [],
                "type": "mean"
              }
            ]
          ],
          "tags": [
            {
              "key": "pid",
              "operator": "=~",
              "value": "/^$job$/"
            }
          ],
          "useBackend": false
        }
      ],
      "title": "Mem Use",
      "type": "timeseries"
    },
    {
      "datasource": {
        "type": "prometheus",
        "uid": "${datasource}"
      },
      "fieldConfig": {
        "defaults": {
          "color": {
            "mode": "palette-classic"
          },
          "custom": {
            "axisBorderShow": false,
            "axisCenteredZero": false,
            "axisColorMode": "text",
            "axisLabel": "",
            "axisPlacement": "auto",
            "barAlignment": 0,
            "drawStyle": "line",
            "fillOpacity": 0,
            "gradientMode": "none",
            "hideFrom": {
              "legend": false,
              "tooltip": false,
              "viz": false
            },
            "insertNulls": false,
            "lineInterpolation": "linear",
            "lineWidth": 1,
            "pointSize": 5,
            "scaleDistribution": {
              "type": "linear"
            },
            "showPoints": "auto",
            "spanNulls": false,
            "stacking": {
              "group": "A",
              "mode": "none"
            },
            "thresholdsStyle": {
              "mode": "off"
            }
          },
          "mappings": [],
          "thresholds": {
            "mode": "absolute",
            "steps": [
              {
                "color": "green",
                "value": null
              },
              {
                "color": "red",
                "value": 80
              }
            ]
          },
          "unit": "decbytes"
        },
        "overrides": []
      },
      "gridPos": {
        "h": 8,
        "w": 24,
        "x": 0,
        "y": 17
      },
      "id": 8,
      "options": {
        "legend": {
          "calcs": [],
          "displayMode": "list",
          "placement": "bottom",
          "showLegend": true
        },
        "tooltip": {
          "mode": "single",
          "sort": "none"
        }
      },
      "targets": [
        {
          "alias": "$tag_pid",
          "datasource": {
            "type": "prometheus",
            "uid": "${datasource}"
          },
          "disableTextWrap": false,
          "editorMode": "builder",
          "expr": "proc_disk_use{instance=~\"$job\"}",
          "fullMetaSearch": false,
          "groupBy": [
            {
              "params": [
                "$cusInterval"
              ],
              "type": "time"
            },
            {
              "params": [
                "pid"
              ],
              "type": "tag"
            }
          ],
          "includeNullMetadata": true,
          "legendFormat": "{{instance}}",
          "measurement": "proc_disk_use",
          "orderByTime": "ASC",
          "policy": "default",
          "range": true,
          "refId": "A",
          "resultFormat": "time_series",
          "select": [
            [
              {
                "params": [
                  "disk_use"
                ],
                "type": "field"
              },
              {
                "params": [],
                "type": "mean"
              }
            ]
          ],
          "tags": [
            {
              "key": "pid",
              "operator": "=~",
              "value": "/^$job$/"
            }
          ],
          "useBackend": false
        }
      ],
      "title": "Disk Use",
      "type": "timeseries"
    }
  ],
  "refresh": "5s",
  "schemaVersion": 39,
  "tags": [],
  "templating": {
    "list": [
      {
        "current": {
          "selected": false,
          "text": "demo-cluster-1",
          "value": "ddpv7f96y42kgd"
        },
        "hide": 0,
        "includeAll": false,
        "label": "Cluster",
        "multi": false,
        "name": "datasource",
        "options": [],
        "query": "prometheus",
        "queryValue": "",
        "refresh": 1,
        "regex": "/^(?!.*default).*$/",
        "skipUrlSync": false,
        "type": "datasource"
      },
      {
        "current": {
          "selected": false,
          "text": "All",
          "value": "$__all"
        },
        "datasource": {
          "type": "prometheus",
          "uid": "${datasource}"
        },
        "definition": "label_values(proc_cpu_use,instance)",
        "hide": 0,
        "includeAll": true,
        "label": "Job",
        "multi": false,
        "name": "job",
        "options": [],
        "query": {
          "qryType": 1,
          "query": "label_values(proc_cpu_use,instance)",
          "refId": "PrometheusVariableQueryEditor-VariableQuery"
        },
        "refresh": 2,
        "regex": "",
        "skipUrlSync": false,
        "sort": 0,
        "type": "query"
      },
      {
        "auto": false,
        "auto_count": 30,
        "auto_min": "10s",
        "current": {
          "selected": false,
          "text": "5m",
          "value": "5m"
        },
        "hide": 0,
        "label": "Interval",
        "name": "cusInterval",
        "options": [
          {
            "selected": false,
            "text": "10s",
            "value": "10s"
          },
          {
            "selected": false,
            "text": "30s",
            "value": "30s"
          },
          {
            "selected": false,
            "text": "1m",
            "value": "1m"
          },
          {
            "selected": true,
            "text": "5m",
            "value": "5m"
          },
          {
            "selected": false,
            "text": "10m",
            "value": "10m"
          },
          {
            "selected": false,
            "text": "15m",
            "value": "15m"
          }
        ],
        "query": "10s, 30s,1m, 5m,10m, 15m",
        "queryValue": "",
        "refresh": 2,
        "skipUrlSync": false,
        "type": "interval"
      }
    ]
  },
  "time": {
    "from": "now-30m",
    "to": "now"
  },
  "timepicker": {},
  "timezone": "",
  "title": "Job Overview - Prometheus",
  "uid": "eduwwyuzispvke",
  "version": 16,
  "weekStart": ""
}